iml/__init__.py
i_ML-0.0.1.dist-info/LICENSE
i_ML-0.0.1.dist-info/METADATA
i_ML-0.0.1.dist-info/WHEEL
i_ML-0.0.1.dist-info/top_level.txt
i_ML-0.0.1.dist-info/RECORD
